VAL_LabelImgs/__init__.py
VAL_LabelImgs/default_imgs.yaml
VAL_LabelImgs/main.py
VAL_LabelImgs/mainapp.py
VAL_LabelImgs/Conda/__init__.py
VAL_LabelImgs/data/coco.yaml
VAL_LabelImgs/data/predefined_classes.txt
VAL_LabelImgs/libs/__init__.py
VAL_LabelImgs/libs/canvas.py
VAL_LabelImgs/libs/change_labels.py
VAL_LabelImgs/libs/colorDialog.py
VAL_LabelImgs/libs/combobox.py
VAL_LabelImgs/libs/constants.py
VAL_LabelImgs/libs/create_ml_io.py
VAL_LabelImgs/libs/download_e.py
VAL_LabelImgs/libs/hashableQListWidgetItem.py
VAL_LabelImgs/libs/labelDialog.py
VAL_LabelImgs/libs/labelFile.py
VAL_LabelImgs/libs/label_to_csv.py
VAL_LabelImgs/libs/pascal_voc_io.py
VAL_LabelImgs/libs/repeat_filter.py
VAL_LabelImgs/libs/resources.py
VAL_LabelImgs/libs/settings.py
VAL_LabelImgs/libs/shape.py
VAL_LabelImgs/libs/stringBundle.py
VAL_LabelImgs/libs/toolBar.py
VAL_LabelImgs/libs/ustr.py
VAL_LabelImgs/libs/utils.py
VAL_LabelImgs/libs/yolo_io.py
VAL_LabelImgs/libs/zoomWidget.py
VAL_LabelImgs/ultralytics/__init__.py
VAL_LabelImgs/ultralytics/cfg/__init__.py
VAL_LabelImgs/ultralytics/cfg/create_default_yaml.py
VAL_LabelImgs/ultralytics/cfg/default.yaml
VAL_LabelImgs/ultralytics/data/__init__.py
VAL_LabelImgs/ultralytics/data/annotator.py
VAL_LabelImgs/ultralytics/data/augment.py
VAL_LabelImgs/ultralytics/data/base.py
VAL_LabelImgs/ultralytics/data/build.py
VAL_LabelImgs/ultralytics/data/converter.py
VAL_LabelImgs/ultralytics/data/dataset.py
VAL_LabelImgs/ultralytics/data/loaders.py
VAL_LabelImgs/ultralytics/data/split_dota.py
VAL_LabelImgs/ultralytics/data/utils.py
VAL_LabelImgs/ultralytics/data/dataloaders/__init__.py
VAL_LabelImgs/ultralytics/data/explorer/__init__.py
VAL_LabelImgs/ultralytics/data/explorer/explorer.py
VAL_LabelImgs/ultralytics/data/explorer/utils.py
VAL_LabelImgs/ultralytics/data/explorer/gui/__init__.py
VAL_LabelImgs/ultralytics/data/explorer/gui/dash.py
VAL_LabelImgs/ultralytics/engine/__init__.py
VAL_LabelImgs/ultralytics/engine/exporter.py
VAL_LabelImgs-1.0.0.dist-info/METADATA
VAL_LabelImgs-1.0.0.dist-info/WHEEL
VAL_LabelImgs-1.0.0.dist-info/entry_points.txt
VAL_LabelImgs-1.0.0.dist-info/top_level.txt
VAL_LabelImgs-1.0.0.dist-info/RECORD
