Metadata-Version: 2.1
Name: VAL_LabelImgs
Version: 1.0.0
Requires-Dist: opencv-python
Requires-Dist: requests
Requires-Dist: psutil
Requires-Dist: tqdm
Requires-Dist: matplotlib
Requires-Dist: pyyaml
Requires-Dist: pandas
Requires-Dist: numpy
Requires-Dist: torch
Requires-Dist: thop
Requires-Dist: torchvision
Requires-Dist: ultralytics-thop
Requires-Dist: urllib3
Requires-Dist: Werkzeug
Requires-Dist: yolov6
Requires-Dist: pycocotools
Requires-Dist: PyQt5
Requires-Dist: lxml
